wformat/__init__.py
wformat/__main__.py
wformat/clang_format.py
wformat/cli_app.py
wformat/daemon.py
wformat/normalizer.py
wformat/uncrustify.py
wformat/utils.py
wformat/wformat.py
wformat/bin/clang-format.exe
wformat/bin/uncrustify.exe
wformat/bin/uncrustify.pdb
wformat/data/.clang-format
wformat/data/uncrustify.cfg
wformat-0.1.6.dist-info/licenses/LICENSE
wformat-0.1.6.dist-info/METADATA
wformat-0.1.6.dist-info/WHEEL
wformat-0.1.6.dist-info/entry_points.txt
wformat-0.1.6.dist-info/top_level.txt
wformat-0.1.6.dist-info/RECORD
