Metadata-Version: 2.4
Name: wformat
Version: 0.1.6
Summary: Opinionated code formatter for C++ code.
Author: Ziwei Wei
License-Expression: MIT
Classifier: Programming Language :: Python :: 3
Requires-Python: >=3.8
License-File: LICENSE
Requires-Dist: tree-sitter
Requires-Dist: tree-sitter-cpp
Provides-Extra: test
Requires-Dist: pytest>=7.0; extra == "test"
Provides-Extra: build
Requires-Dist: build; extra == "build"
Requires-Dist: twine; extra == "build"
Requires-Dist: wheel; extra == "build"
Requires-Dist: pyinstaller<7,>=6.15; extra == "build"
Dynamic: license-file
